django_ssr/__init__.py
django_ssr/backends.py
django_ssr/helpers.py
django_ssr/middleware.py
django_ssr/settings.py
django_ssr-0.0.1.dist-info/DESCRIPTION.rst
django_ssr-0.0.1.dist-info/LICENSE.txt
django_ssr-0.0.1.dist-info/METADATA
django_ssr-0.0.1.dist-info/RECORD
django_ssr-0.0.1.dist-info/WHEEL
django_ssr-0.0.1.dist-info/metadata.json
django_ssr-0.0.1.dist-info/top_level.txt
