Metadata-Version: 2.0
Name: django-ssr
Version: 0.0.1
Summary: SSR for django project
Home-page: https://github.com/greyzmeem/django-ssr
Author: Andrey Maslov
Author-email: greyzmeem@gmail.com
License: MIT
Platform: UNKNOWN
Classifier: Development Status :: 2 - Pre-Alpha
Classifier: Programming Language :: Python :: 3 :: Only
Classifier: Programming Language :: Python :: 3.5
Classifier: Programming Language :: Python :: 3.6
Classifier: Framework :: Django
Classifier: Framework :: Django :: 1.11
Classifier: Framework :: Django :: 2.0
Classifier: Operating System :: OS Independent
Classifier: Topic :: Internet :: WWW/HTTP
Classifier: License :: OSI Approved :: MIT License
Requires-Python: >=3.5,<3.8
Requires-Dist: django (>=1.11,<2.2)
Requires-Dist: requests (>=2)
